[
 {
  "title": "【ざまぁw】企画横取り上司に隠し機能仕込んだらwww",
  "summary": "イッチの企画資料を上司が横取り。仕掛けた隠し機能で逆転！"
 },
 {
  "title": "【ざまぁw】フリマで詐欺ろうとした奴が逆に警察沙汰になった件ｗｗｗ",
  "summary": "フリマで詐欺を企んだ購入者が自滅する話"
 },
 {
  "title": "【新商品】部長の「俺が考えた」発言に仕掛けた仕返しｗ",
  "summary": "部長が企画を横取り！しかしイッチの仕掛けが！"
 },
 {
  "title": "【DQN隣人】迷惑駐車を合法的に潰した話ｗｗｗ",
  "summary": "迷惑駐車する隣人にイベント開催を盾に合法的に反撃！"
 },
 {
  "title": "【罠発動】奢り厨を合法的に爆散させた話ｗｗｗ",
  "summary": "奢られ前提の地雷女を、特殊な店の予約でスカッと撃退した話。"
 },
 {
  "title": "【悲報】結婚式で「お前の余興つまらん」と暴言の義兄、俺の隠し玉で爆死ｗｗｗ",
  "summary": "式で恥をかかされた義兄に、新郎である俺が仕掛けた痛快な逆襲劇。"
 },
 {
  "title": "【悲報】俺の作成した見積書を盗んだ先輩、客前で大恥をかくｗｗｗ",
  "summary": "見積書の盗用を企む先輩を、あえて残したミスで公衆の面前で追い込む。"
 },
 {
  "title": "【悲報】傲慢な同僚、俺のPCでプレゼンしようとしてデスクトップを全開で公開w",
  "summary": "盗用を目論む同僚に恥をかかせる罠を仕掛けていた話"
 },
 {
  "title": "【横取り婆】希少植物を強奪→速攻で自滅ワロタｗｗｗ",
  "summary": "世話が難しい希少植物を横取りした近所の婆が自滅した話。"
 },
 {
  "title": "【激辛】俺の挑戦飯を横取りした結果ｗｗｗ",
  "summary": "激辛チャレンジメニューを勝手に食べた客が自滅した話。"
 },
 {
  "title": "【ざまぁ】俺の模型バカにした隣人が自滅ワロタwww",
  "summary": "俺の模型趣味を馬鹿にした隣人が、勝手に持ち去った未完成品で恥をかく話"
 },
 {
  "title": "【GJ】職場の冷蔵庫荒らしに不味い健康ドリンク飲ませたったｗｗｗ",
  "summary": "職場の冷蔵庫から勝手に飲み物を盗む同僚に不味い健康ドリンクで反撃した話。"
 },
 {
  "title": "【悲報】俺の高級イヤホンを「壊したから捨てるわ」と抜かす後輩に実家送りにした結果www",
  "summary": "イヤホンをパクった後輩をGPSで制裁する話"
 },
 {
  "title": "【スカッと】限定イベント参加権を横取りしようとした後輩ざまぁwww",
  "summary": "限定イベントの参加権を横取りしようとした後輩が、後で激しく後悔した話。"
 },
 {
  "title": "【ざまぁ】契約P無断駐車にタイヤロック刺さったｗｗｗ",
  "summary": "契約駐車場の無断利用者にタイヤロックでざまぁ。"
 },
 {
  "title": "オーダー靴の値引きゴネた客、逆に高額掴まされるｗｗｗ",
  "summary": "俺の靴工房で値引きゴネたDQN客をスカッと合法的に撃退。"
 },
 {
  "title": "図書館のPC席占拠DQN、カウンターで逝くｗｗｗ",
  "summary": "図書館のPC席を占拠するDQNを、予約システムで合法的に追い出した話。"
 },
 {
  "title": "【悲報】俺の高級ペンを泥棒した同僚、会議で盛大に大恥をかくｗｗｗ",
  "summary": "同僚にペンを盗まれたが、実はそれ〇〇用だった話"
 },
 {
  "title": "【悲報】強欲な義姉に「私の特注ケーキ」を奪われたんだがｗｗｗ",
  "summary": "勝手にケーキを奪った強欲義姉に激辛の罠で反撃する話"
 },
 {
  "title": "【スカッと】勘違いDQN客、本物の社長に遭遇ｗｗｗ",
  "summary": "いつも偉そうなDQN客が、本物の社長の前で大恥かいてざまぁ！"
 },
 {
  "title": "【借りパク】自作プランター持ち去ったDQNが自滅ワロタｗｗｗ",
  "summary": "自作の特殊プランターを借りパクした隣のDQNが自滅した話。"
 },
 {
  "title": "【朗報】部長が俺の特別メニュー横取りwww",
  "summary": "部長が俺の健康食を「VIPメニュー」と勘違いして奪い、悶絶した話。"
 },
 {
  "title": "【ざまぁ】俺の自作盆栽オブジェをパクったDQN、展示会で大恥ｗｗｗ",
  "summary": "自作の盆栽オブジェをパクられたが、展示会で仕掛けが発動してざまぁｗｗｗ"
 },
 {
  "title": "【悲報】俺の高級イヤホン盗んだ自称音楽通の同僚、大音量の爆音で昇天ｗｗｗ",
  "summary": "盗品イヤホンで爆音を鳴らした同僚が赤っ恥をかく話"
 },
 {
  "title": "金持ってるって絡んでくるDQNに自作の宝箱見せたらｗｗｗ",
  "summary": "金目当てに絡んできたDQNが、イッチの宝箱の中身を見て恥をかく話。"
 },
 {
  "title": "【悲報】俺の高級傘をパクった先輩、傘の性能を知らずに大惨事www",
  "summary": "傘をパクった先輩に、防犯ブザー機能付きの特注傘で制裁を下す話。"
 },
 {
  "title": "【緊急告知】DQN上司、会議室横取りで公開処刑ｗｗｗ",
  "summary": "予約した会議室を横取りした上司に、イッチがプロジェクターの仕掛けで反撃する話。"
 },
 {
  "title": "【痛快】奪った割引券が使えずDQN発狂ｗｗｗ",
  "summary": "DQNが奪った割引券が使えず恥をかく痛快な話"
 },
 {
  "title": "昼休み奪った上司がプレゼンで大恥かいてワロタ【ざまぁｗｗｗ】",
  "summary": "休憩を邪魔する上司が、知るべき情報を見逃し自滅。"
 },
 {
  "title": "【スカッ】社内ツールの裏技で先輩ざまぁｗｗｗ",
  "summary": "社内ツールの裏技で、情報を出し渋る先輩に反撃した話。"
 },
 {
  "title": "【ざまぁ】俺のゲー配信の裏技パクった奴が公開処刑ｗｗｗ",
  "summary": "ゲーム配信で俺の裏技をパクったマウント先輩が自爆した話。"
 },
 {
  "title": "【悲報】高級店で全額奢らされた俺、会計で神対応してDQN女を凍りつかせたわwww",
  "summary": "奢り前提の女を店との連携で撃退"
 },
 {
  "title": "【ざまぁ】ゴミ出しマナー違反の隣人、自作罠で撃沈www",
  "summary": "マンションのゴミ出しルール違反の隣人を、自作の罠で撃退した話。"
 },
 {
  "title": "誰も読まない社内報担当、頑張ったら上司が自爆ｗｗｗ",
  "summary": "社内報を軽視した上司が、読み落としで大恥をかいた話。"
 },
 {
  "title": "【悲報】ワイの特注椅子を奪った同僚、座った瞬間に大惨事へwww",
  "summary": "腰痛持ちのイッチの高級椅子を奪った同僚を、細工済みの椅子のバネで制裁。"
 },
 {
  "title": "【スカッと】物々交換会でマダムが自爆ｗｗｗ",
  "summary": "交換会で貴重品を横取りしたマダムが自滅する話。"
 },
 {
  "title": "【ざまぁ】ジャンク趣味を馬鹿にしたDQNが自滅ワロタｗｗｗ",
  "summary": "イッチのジャンク修理趣味を馬鹿にしたDQNが、限定品を壊して自爆する話。"
 },
 {
  "title": "自作テンプレをバカにした新人DQNｗｗｗ",
  "summary": "長年作った業務テンプレをバカにした新人DQNが自滅した話。"
 },
 {
  "title": "【万引きGメン】店員に逆ギレ→まさかの展開w",
  "summary": "万引き疑われ逆ギレ→店員まさかの神対応w"
 },
 {
  "title": "【スカッと】共有プリンターを私物化するDQN先輩が自爆ｗｗｗ",
  "summary": "職場の共有3Dプリンターを私物化する先輩が、定期メンテで痛い目に遭う話"
 },
 {
  "title": "【胸糞】共有ロッカー横取り先輩→まさかの自爆ｗｗｗ",
  "summary": "職場の共有ロッカーを独占する先輩が、まさかの自爆でざまぁな話。"
 },
 {
  "title": "【ざまぁ】俺のPC借りた先輩が伝説残したｗｗｗ",
  "summary": "勝手にPCを借りた先輩が、特殊設定のせいで大恥をかく話。"
 },
 {
  "title": "【自作】マニュアル馬鹿にした新人ざまぁｗｗｗ",
  "summary": "イッチが作ったマニュアルを馬鹿にした新人が自滅。"
 },
 {
  "title": "【クソ同僚】ヘッドホンしてたら何言ってもいいとでも？www",
  "summary": "ダミーのヘッドホンで、私用電話で大声出す同僚を撃退した話。"
 },
 {
  "title": "自作アクセ譲ったらDQN同僚が夜の街でピカチュウになっててワロタｗｗｗ",
  "summary": "見栄っ張りな同僚が、イッチの自作蓄光アクセで大恥。"
 },
 {
  "title": "【スカッと】俺の「情報術」をバカにしたDQN先輩が自爆www",
  "summary": "俺の独自の情報整理を破壊した先輩が大恥かいて自爆ｗｗｗ"
 },
 {
  "title": "枯らし屋DQN、特殊鉢で顔面蒼白www",
  "summary": "共有植物を枯らすDQNに、イッチの特殊鉢が炸裂！"
 },
 {
  "title": "【天才かよ】俺のPC設定でDQN同僚を撃退ｗｗｗ",
  "summary": "PC設定でDQN同僚を撃退！天才かよwww"
 },
 {
  "title": "【ざまぁw】俺の安物スプレーパクったDQN、ドリアン臭まみれで大恥ｗｗｗ",
  "summary": "安物と馬鹿にされた特殊スプレーを盗んだDQNが、ドリアン臭まみれで大恥をかく話。"
 },
 {
  "title": "【スカッと】共有ボードを私物化する先輩が自爆ｗｗｗ",
  "summary": "共有ホワイトボードを私物化する先輩を合法的に撃退！"
 },
 {
  "title": "【ざまぁ】俺のキーボードパクった先輩がプレゼン爆死ｗｗｗ",
  "summary": "勝手にキーボードを持ち去った先輩がプレゼンで大恥かいた話。"
 },
 {
  "title": "DQNが勝手に摘んだハーブ、特殊すぎて大惨事ｗｗｗ",
  "summary": "共有ハーブを横取りしたDQNが虫にたかられてざまぁｗｗ"
 },
 {
  "title": "【朗報】香水DQN、イッチのガチ空気清浄機で自爆ｗｗｗ",
  "summary": "共有休憩室を香水で私物化するDQNを、イッチの空気清浄機が撃退する話。"
 },
 {
  "title": "【店員黙認】勝手に値切るDQN客に最終兵器発動w",
  "summary": "強引に値切る客を店員と連携して撃退"
 },
 {
  "title": "【奇形マウス】俺の愛用マウス奪ったDQNが自滅ざまぁｗｗｗ",
  "summary": "イッチの自作マウスを馬鹿にして奪ったDQNが使いこなせず自滅する話。"
 },
 {
  "title": "【神対応】職場の共有PC、勝手に使おうとしたDQNを秒で撃退www",
  "summary": "共有PCの空き時間を勝手に申請するDQNに、イッチが巧妙な罠を仕掛ける"
 },
 {
  "title": "【神】俺の弁当を奪ったDQN、まさかの自滅w",
  "summary": "弁当奪ったDQN、まさかの自滅w"
 },
 {
  "title": "【腹立つ】隣人のゴミ、全部俺んちの前に置くなｗｗｗ",
  "summary": "隣人のゴミ出しルール違反に制裁！"
 },
 {
  "title": "俺のカップ奪ったDQN、顔面真っ赤で逃走ｗｗｗ",
  "summary": "自作のカップを横取りした同僚が、仕掛けで赤っ恥！"
 },
 {
  "title": "自作の『激辛激マズ弁当』を盗み食いする同僚を罠に嵌めた結果ｗｗｗ",
  "summary": "盗み食い常習犯の同僚に、激辛実験用の弁当を喰わせて撃退した話。"
 },
 {
  "title": "【備えあれば】防災備蓄を笑った先輩が社内孤立で自爆ｗｗｗ",
  "summary": "デスクの防災備蓄を笑った先輩が停電時に困り果てた話。"
 },
 {
  "title": "【朗報】DQN先輩の鍵独占、館内放送でざまぁｗｗｗ",
  "summary": "共有鍵を独占するDQN先輩に、イッチが自動返却システムで反撃。"
 },
 {
  "title": "プレゼン資料荒らしたDQN同僚、まさかのオチで顔面蒼白www",
  "summary": "プレゼン資料を破壊しようとしたDQN同僚が、イッチの罠にはまり自爆する話。"
 },
 {
  "title": "【DQN乙www】休憩室椅子独占DQNに仕掛けた結果ｗｗｗ",
  "summary": "休憩室椅子独占DQNにマッサージチェアで仕返し！"
 },
 {
  "title": "【ざまぁ】共有高級コーヒー横取りDQN、まさかの自爆ｗｗｗ",
  "summary": "職場の共有高級コーヒーを独占するDQN同僚を、イッチが痛快に撃退！"
 },
 {
  "title": "【裏技】先輩のPC知識マウント、まさかの自爆www",
  "summary": "PC知識マウント先輩、イッチのPCで自滅ww"
 },
 {
  "title": "【スカッと】フリマでマウント転売ヤー爆死www",
  "summary": "激レア品を巡りDQN転売ヤーがコメントでマウント→イッチの罠で自爆"
 },
 {
  "title": "【超絶】仕事猫化する同僚に,俺のPC設定で反撃！www",
  "summary": "仕事猫同僚にPC設定で天誅！w"
 },
 {
  "title": "【悲報】俺の愛車を勝手にカスタムしたDQN、まさかの自滅ｗｗｗ",
  "summary": "愛車を勝手にいじったDQNが走行不能になり顔面蒼白"
 },
 {
  "title": "デモ用ペンを借りパクDQNが契約書で顔面蒼白ｗｗｗ",
  "summary": "備品を借りパクするDQNに、イッチが仕掛けたデモ用ペンが炸裂！"
 },
 {
  "title": "【自滅】ウォーターサーバー空ボトル放置DQNに天罰！【ざまぁ】",
  "summary": "ウォーターサーバーの空ボトルを放置するDQNにイッチが仕返し！"
 },
 {
  "title": "忘れ物ボックス勝手に捨てたDQNが自爆ｗｗｗ",
  "summary": "忘れ物ボックス管理のイッチにDQN同僚が勝手に廃棄→まさかのDQN自滅"
 },
 {
  "title": "自作ペンをバカにしたDQN、会議で自滅ワロタｗｗｗ",
  "summary": "イッチの自作ペンを横取りしたDQNが、会議で大恥をかく話。"
 },
 {
  "title": "掲示物剥がした先輩DQNざまぁｗｗｗ",
  "summary": "共有掲示物を勝手に剥がした先輩DQNが、イッチの罠で大恥をかく話。"
 },
 {
  "title": "【ざまぁ】共有プロジェクター設定いじるDQN、会議で大恥ww",
  "summary": "共有プロジェクターを私物化するDQNが会議で自滅した話。"
 },
 {
  "title": "【会議】内職DQN、マイクONする度ミュートで焦り草",
  "summary": "オンライン会議で内職するDQN同僚を、イッチが巧妙な設定でミュートにし、痛快に反撃した話。"
 },
 {
  "title": "職場チャイムを独占したDQN、秒で詰むｗｗｗ",
  "summary": "職場チャイムを私物化したDQNが自動制御で自爆。"
 },
 {
  "title": "【価値ねぇw】限定バッジ晒し上げDQNが、まさかの自滅ｗｗｗ",
  "summary": "イッチの集める限定バッジを馬鹿にしたDQN、大恥！"
 },
 {
  "title": "【スカッと】共有空調DQN、自動制御で爆死wwww",
  "summary": "共有スペースの空調を勝手にいじるDQNをスマートリモコンで撃退した話。"
 },
 {
  "title": "【社内報DQN】悪意の写真が消滅ｗｗｗ",
  "summary": "社内報で悪意ある写真を載せるDQNが、イッチの管理権限で自爆する話。"
 },
 {
  "title": "【DQN撃退】俺の充電器勝手に使う奴まじキモい→まさかの結末ｗｗ",
  "summary": "私物充電器を勝手に使うDQNに、イッチが奇策で反撃する話。"
 },
 {
  "title": "イベント飾り潰しDQN、まさかの自爆ｗｗｗ",
  "summary": "イベントの飾り付けを破壊したDQNが、イッチの機転で痛い目に。"
 },
 {
  "title": "【DQN先輩】アイデア泥棒撃退大作戦ｗｗｗ",
  "summary": "アイデアを横取りするDQN先輩をイッチが痛快に撃退！"
 },
 {
  "title": "共有チャリ独占DQN、ワイのシステムで撃沈ｗｗｗ",
  "summary": "職場の共有自転車を私物化するDQNを、イッチが自作の予約システムで撃退した話。"
 },
 {
  "title": "DQN爆音イヤホン、音漏れ対策したら自爆したｗｗｗ",
  "summary": "職場で爆音で音漏れするDQNイヤホンに、イッチが独自ノイズ発生器で反撃！"
 },
 {
  "title": "【ざまぁ】共有マーカー独占DQN、会議で自爆ｗｗｗ",
  "summary": "共有マーカーを独占するDQNが、消えるマーカーで自滅！"
 },
 {
  "title": "【裏技】共有PCの奇妙なエラー、犯人はアイツｗｗ",
  "summary": "共有PCの不具合、犯人に仕掛けた罠が炸裂！"
 },
 {
  "title": "告知ジャックDQN、緊急システムで撃沈ｗｗｗ",
  "summary": "社内告知を私物化するDQNに、イッチが緊急システムで反撃。"
 }
]